gym_adr/__init__.py
gym_adr/adr.py
gym_adr/assets/models/high_poly_sphere.obj
gym_adr/assets/models/low_poly_sphere.obj
gym_adr/assets/models/otv.dae
gym_adr/assets/models/plane.obj
gym_adr/assets/models/sat.dae
gym_adr/assets/shaders/pbr.frag
gym_adr/assets/shaders/pbr.vert
gym_adr/assets/shaders/post_process.frag
gym_adr/assets/shaders/post_process.vert
gym_adr/assets/shaders/shadow_f.glsl
gym_adr/assets/shaders/shadow_v.glsl
gym_adr/assets/shaders/sun.frag
gym_adr/assets/shaders/sun.vert
gym_adr/assets/skybox/back.png
gym_adr/assets/skybox/bottom.png
gym_adr/assets/skybox/front.png
gym_adr/assets/skybox/left.png
gym_adr/assets/skybox/right.png
gym_adr/assets/skybox/top.png
gym_adr/assets/textures/cloud.png
gym_adr/assets/textures/earth_bm3.png
gym_adr/assets/textures/earth_emission.png
gym_adr/assets/textures/earth_specular.jpg
gym_adr/assets/textures/earth_topography.png
gym_adr/assets/textures/otv_albedo.png
gym_adr/assets/textures/otv_emission.png
gym_adr/assets/textures/otv_texture.png
gym_adr/assets/textures/sat_texture.png
gym_adr/rendering/rendering.py
gym_adr/rendering/utils.py
gym_adr/space_physics/__init__.py
gym_adr/space_physics/custom_low_level.py
gym_adr/space_physics/custom_maneuvres.py
gym_adr/space_physics/custom_orbit.py
gym_adr/space_physics/in_plane_physics.py
gym_adr/space_physics/simulator.py
gym_adr-0.1.0.dist-info/LICENSE
gym_adr-0.1.0.dist-info/METADATA
gym_adr-0.1.0.dist-info/WHEEL
gym_adr-0.1.0.dist-info/RECORD
