Metadata-Version: 2.3
Name: gym-adr
Version: 0.1.0
Summary: A gymnasium environment for ADR.
License: Apache-2.0
Author: Hugo de Rohan Willner
Author-email: hugoderohanwillner@gmail.com
Requires-Python: >=3.9,<3.11
Classifier: License :: OSI Approved :: Apache Software License
Classifier: Programming Language :: Python :: 3
Classifier: Programming Language :: Python :: 3.9
Classifier: Programming Language :: Python :: 3.10
Provides-Extra: example
Requires-Dist: astropy (==5.2.2)
Requires-Dist: gymnasium (>=1.0.0,<2.0.0)
Requires-Dist: numba (==0.60)
Requires-Dist: numpy (==1.24.4)
Requires-Dist: panda3d (>=1.10.15,<2.0.0)
Requires-Dist: poliastro (>=0.17.0,<0.18.0)
Requires-Dist: screeninfo (>=0.8.1,<0.9.0)
Requires-Dist: stable-baselines3 (>=2.6.0,<3.0.0) ; extra == "example"
Requires-Dist: tqdm (>=4.67.1,<5.0.0)
Requires-Dist: wandb (>=0.19.7,<0.20.0)
